falcondale-0.2.4.dist-info/METADATA
falcondale-0.2.4.dist-info/WHEEL
falcondale/__init__.py
falcondale/classifiers.py
falcondale/clustering.py
falcondale/data.py
falcondale/feature_selection.py
falcondale/helpers/__init__.py
falcondale/helpers/kernels.py
falcondale/helpers/mutual_information.py
falcondale/helpers/qnn.py
falcondale/helpers/qsvc.py
falcondale/main.py
falcondale/solvers.py
falcondale-0.2.4.dist-info/RECORD
