Metadata-Version: 2.1
Name: falcondale
Version: 0.2.4
Summary: Falcondale SDK
Author-Email: Stafford Computing LLC <info@staffordcomputing.com>
License: MIT
Project-URL: Homepage, https://github.com/stafford-computing/falcondale-sdk
Project-URL: Documentation, https://falcondale.readthedocs.io/
Requires-Python: <3.12,>=3.10
Requires-Dist: pandas>=2.2.1
Requires-Dist: ydata-profiling>=4.5.1
Requires-Dist: scikit-learn>=1.3.0
Requires-Dist: ipywidgets>=8.1.1
Requires-Dist: torch>=2.0.1
Requires-Dist: pennylane>=0.35.1
Requires-Dist: qiskit>=1.0.2
Requires-Dist: qiskit-machine-learning>=0.7.2
Requires-Dist: qiskit-aer>=0.14.0.1
Requires-Dist: dimod>=0.12.12
Requires-Dist: dwave-neal>=0.6.0
Requires-Dist: dwave-cloud-client>=0.10.6
Requires-Dist: requests[socks]>=2.31.0
Requires-Dist: qiskit-optimization>=0.6.1
Requires-Dist: qiskit-algorithms>=0.3.0
Requires-Dist: apqc>=0.1.3
Requires-Dist: simulated-bifurcation>=1.2.0
